odoo/addons/sentry/README.rst
odoo/addons/sentry/__init__.py
odoo/addons/sentry/__manifest__.py
odoo/addons/sentry/const.py
odoo/addons/sentry/generalutils.py
odoo/addons/sentry/hooks.py
odoo/addons/sentry/logutils.py
odoo/addons/sentry/processor.py
odoo/addons/sentry/i18n/ca.po
odoo/addons/sentry/i18n/it.po
odoo/addons/sentry/i18n/sentry.pot
odoo/addons/sentry/i18n/zh_CN.po
odoo/addons/sentry/readme/CONFIGURE.md
odoo/addons/sentry/readme/CONTRIBUTORS.md
odoo/addons/sentry/readme/CREDITS.md
odoo/addons/sentry/readme/DESCRIPTION.md
odoo/addons/sentry/readme/INSTALL.md
odoo/addons/sentry/readme/ROADMAP.md
odoo/addons/sentry/readme/USAGE.md
odoo/addons/sentry/static/description/icon.png
odoo/addons/sentry/static/description/index.html
odoo/addons/sentry/tests/__init__.py
odoo/addons/sentry/tests/test_client.py
odoo/addons/sentry/tests/test_generalutils.py
odoo/addons/sentry/tests/test_logutils.py
odoo/addons/sentry/tests/test_processor.py
odoo_addon_sentry-18.0.1.0.3.dist-info/METADATA
odoo_addon_sentry-18.0.1.0.3.dist-info/WHEEL
odoo_addon_sentry-18.0.1.0.3.dist-info/top_level.txt
odoo_addon_sentry-18.0.1.0.3.dist-info/RECORD
