Metadata-Version: 2.1
Name: odoo-addon-sentry
Version: 18.0.1.0.3
Requires-Python: >=3.10
Requires-Dist: odoo==18.0.*
Requires-Dist: sentry_sdk>=2.0.0,<=2.22.0
Summary: Report Odoo errors to Sentry
Home-page: https://github.com/OCA/server-tools
License: AGPL-3
Author: Mohammed Barsi,Versada,Nicolas JEUDY,Odoo Community Association (OCA),Vauxoo
Author-email: support@odoo-community.org
Classifier: Programming Language :: Python
Classifier: Framework :: Odoo
Classifier: Framework :: Odoo :: 18.0
Classifier: License :: OSI Approved :: GNU Affero General Public License v3
